ZAIScikit/__init__.py
ZAIScikit/bagging.py
ZAIScikit/boosting.py
ZAIScikit/decision_tree.py
ZAIScikit/encoding.py
ZAIScikit/feature_selection.py
ZAIScikit/grid_search.py
ZAIScikit/imputation.py
ZAIScikit/kmeans.py
ZAIScikit/linear_models.py
ZAIScikit/metrics.py
ZAIScikit/mlp.py
ZAIScikit/naive_bayes.py
ZAIScikit/nearest_neighbors.py
ZAIScikit/pca.py
ZAIScikit/scaler.py
ZAIScikit/sklearn_base.py
ZAIScikit/splitting.py
ZAIScikit/utilities.py
ZAIScikit-0.1.2.dist-info/LICENSE
ZAIScikit-0.1.2.dist-info/METADATA
ZAIScikit-0.1.2.dist-info/WHEEL
ZAIScikit-0.1.2.dist-info/top_level.txt
ZAIScikit-0.1.2.dist-info/RECORD
