Metadata-Version: 2.1
Name: ZAIScikit
Version: 0.1.2
Summary: A Machine learning library
Home-page: https://github.com/Zakaria-El-Maachi/ZAI-Scikit
Author: Zakaria
Author-email: zakaria.elmaachi19@gmail.com
Classifier: Programming Language :: Python :: 3
Classifier: License :: OSI Approved :: MIT License
Classifier: Operating System :: OS Independent
Requires-Python: >=3.7
License-File: LICENSE
